govinfo/__init__.py
govinfo/client.py
govinfo/config.py
govinfo/exceptions.py
govinfo/models.py
govinfo/provider.py
govinfo/py.typed
govinfo-0.3.0.dist-info/METADATA
govinfo-0.3.0.dist-info/WHEEL
govinfo-0.3.0.dist-info/RECORD
